weatherunion_mcp/__init__.py
weatherunion_mcp/server.py
weatherunion_mcp-1.0.2.dist-info/METADATA
weatherunion_mcp-1.0.2.dist-info/WHEEL
weatherunion_mcp-1.0.2.dist-info/entry_points.txt
weatherunion_mcp-1.0.2.dist-info/licenses/LICENSE
weatherunion_mcp-1.0.2.dist-info/RECORD
