Metadata-Version: 2.4
Name: weatherunion-mcp
Version: 1.0.2
Summary: Weather Union MCP Server - A Model Context Protocol server for weather data
License-File: LICENSE
Requires-Python: >=3.11
Requires-Dist: fastmcp>=0.2.0
Requires-Dist: python-dotenv>=1.1.0
Requires-Dist: requests>=2.31.0
